postgres_graph_rag/__init__.py
postgres_graph_rag/core.py
postgres_graph_rag/database.py
postgres_graph_rag/extractor.py
postgres_graph_rag/models.py
postgres_graph_rag-0.1.2.dist-info/METADATA
postgres_graph_rag-0.1.2.dist-info/WHEEL
postgres_graph_rag-0.1.2.dist-info/licenses/LICENSE
postgres_graph_rag-0.1.2.dist-info/RECORD
