Metadata-Version: 2.4
Name: postgres-graph-rag
Version: 0.1.2
Summary: A lean GraphRAG library using Postgres/pgvector as the sole database
Project-URL: Homepage, https://github.com/h4gen/postgres-graph-rag
Project-URL: Repository, https://github.com/h4gen/postgres-graph-rag
Author-email: Hagen <hagen@example.com>
License-Expression: MIT
License-File: LICENSE
Classifier: License :: OSI Approved :: MIT License
Classifier: Operating System :: OS Independent
Classifier: Programming Language :: Python :: 3
Requires-Python: >=3.10
Requires-Dist: google-genai>=0.1.0
Requires-Dist: ipykernel>=7.1.0
Requires-Dist: matplotlib>=3.10.8
Requires-Dist: networkx>=3.4.2
Requires-Dist: openai>=1.12.0
Requires-Dist: pandas>=2.2.0
Requires-Dist: pgvector>=0.2.5
Requires-Dist: psycopg[binary,pool]>=3.1.18
Requires-Dist: pydantic>=2.6.0
Requires-Dist: python-dotenv>=1.0.1
Provides-Extra: test
Requires-Dist: pytest-asyncio>=0.23.0; extra == 'test'
Requires-Dist: pytest-mock>=3.12.0; extra == 'test'
Requires-Dist: pytest>=8.0.0; extra == 'test'
